smokescreen/__init__.py
smokescreen/__main__.py
smokescreen/_version.py
smokescreen/datavector.py
smokescreen/encryption.py
smokescreen/param_shifts.py
smokescreen/utils.py
smokescreen-1.5.0.dist-info/METADATA
smokescreen-1.5.0.dist-info/WHEEL
smokescreen-1.5.0.dist-info/entry_points.txt
smokescreen-1.5.0.dist-info/licenses/LICENSE
smokescreen-1.5.0.dist-info/RECORD
