Metadata-Version: 2.4
Name: Smokescreen
Version: 1.5.0
Summary: Smokescreen: DESC Blinding Unified Library. Based on the Muir et al. (2021) data-vector blinding method.
Project-URL: Homepage, https://github.com/LSSTDESC/Smokescreen
Project-URL: Issues, https://github.com/LSSTDESC/Smokescreen/issues
Maintainer-email: Arthur Loureiro <arthur.loureiro@fysik.su.se>
License: BSD 3-Clause License
License-File: LICENSE
Keywords: blinding,cosmology,desc,firecrown,python
Classifier: License :: OSI Approved :: BSD License
Classifier: Operating System :: OS Independent
Classifier: Programming Language :: Python :: 3
Requires-Python: >=3.12
Requires-Dist: astropy>=5.2.0
Requires-Dist: cryptography
Requires-Dist: jsonargparse[signatures]>=4.0
Requires-Dist: numpy>=2.2.0
Requires-Dist: pytest
Requires-Dist: pytest-cov
Requires-Dist: pytest>=7.2.5
Requires-Dist: sacc>=0.12
Requires-Dist: scipy>=1.9.0
Provides-Extra: docs
Requires-Dist: sphinx-rtd-theme; extra == 'docs'
Requires-Dist: sphinx>=7.3.0; extra == 'docs'
Requires-Dist: sphinxcontrib-autoprogram; extra == 'docs'
Requires-Dist: sphinxcontrib-datatemplates; extra == 'docs'
